{
  "builtAt": "2026-06-19T23:29:55.527Z",
  "kind": "component-demo",
  "demoRoot": "..\\..\\..\\components\\lightbox\\demo",
  "files": 5,
  "bytesIn": 8768,
  "bytesOut": 12870,
  "ratio": 1.468,
  "hash": "c8501817fc57",
  "appBundle": "_dist/app.min.js",
  "entries": [
    {
      "rel": "js\\app\\main.jsx",
      "bytesIn": 144,
      "bytesOut": 6619
    },
    {
      "rel": "css/demo.css",
      "bytesIn": 1305,
      "bytesOut": 976
    },
    {
      "rel": "css/theme.css",
      "bytesIn": 3077,
      "bytesOut": 2486
    },
    {
      "rel": "js/boot/loader.mjs",
      "bytesIn": 1271,
      "bytesOut": 909
    },
    {
      "rel": "js/boot/cdn.mjs",
      "bytesIn": 2971,
      "bytesOut": 1880
    }
  ]
}
